kolibri/.env
kolibri/VERSION
kolibri/__init__.py
kolibri/app.py
kolibri/config.py
kolibri/config_loader.py
kolibri/default_configs.py
kolibri/errors.py
kolibri/logger.py
kolibri/metadata.py
kolibri/model_loader.py
kolibri/model_trainer.py
kolibri/registry.py
kolibri/requirements.txt
kolibri/settings.py
kolibri/settings.yaml
kolibri/types.py
kolibri/version.py
kolibri/api/__init__.py
kolibri/api/classification/__init__.py
kolibri/autolearn/__init__.py
kolibri/autolearn/metalearn/__init__.py
kolibri/autolearn/metalearn/metafeature.py
kolibri/autolearn/metalearn/metafeatures.py
kolibri/autolearn/model_zoo/__init__.py
kolibri/autolearn/model_zoo/zoo_classifier.py
kolibri/autolearn/model_zoo/zoo_estimator.py
kolibri/autolearn/model_zoo/zoo_regressor.py
kolibri/automl/__init__.py
kolibri/automl/data_inspection.py
kolibri/backend/__init__.py
kolibri/backend/models.py
kolibri/backend/base/__init__.py
kolibri/backend/base/base_classifier.py
kolibri/backend/base/base_clustering.py
kolibri/backend/base/base_estimator.py
kolibri/backend/base/base_regressor.py
kolibri/backend/base/estimator.py
kolibri/backend/base/nn_model.py
kolibri/backend/bn/BayesianModel.py
kolibri/backend/bn/BayesianNetwork.py
kolibri/backend/bn/CPD.py
kolibri/backend/bn/ContinuousFactor.py
kolibri/backend/bn/DAG.py
kolibri/backend/bn/DiscreteFactor.py
kolibri/backend/bn/DynamicBayesianNetwork.py
kolibri/backend/bn/EliminationOrder.py
kolibri/backend/bn/ExactInference.py
kolibri/backend/bn/FactorGraph.py
kolibri/backend/bn/Independencies.py
kolibri/backend/bn/JointProbabilityDistribution.py
kolibri/backend/bn/JunctionTree.py
kolibri/backend/bn/LinearGaussianCPD.py
kolibri/backend/bn/MarkovChain.py
kolibri/backend/bn/MarkovNetwork.py
kolibri/backend/bn/NaiveBayes.py
kolibri/backend/bn/Sampling.py
kolibri/backend/bn/UndirectedGraph.py
kolibri/backend/bn/__init__.py
kolibri/backend/bn/base_estimator.py
kolibri/backend/bn/base_inference.py
kolibri/backend/bn/bnlearn.py
kolibri/backend/bn/factors_base.py
kolibri_ml-1.1.88.dist-info/LICENCE.txt
kolibri_ml-1.1.88.dist-info/METADATA
kolibri_ml-1.1.88.dist-info/WHEEL
kolibri_ml-1.1.88.dist-info/top_level.txt
kolibri_ml-1.1.88.dist-info/RECORD
