Metadata-Version: 2.1
Name: kolibri-ml
Version: 1.1.88
Summary: Deep Learning and more NLP toolkit
Home-page: 
Author: Mohamed Ben Haddou
Author-email: mbenhaddou@mentis.io
Classifier: Programming Language :: Python :: 3.7
Classifier: Operating System :: OS Independent
Classifier: Development Status :: 4 - Beta
Requires-Python: >=3.7
License-File: LICENCE.txt
Requires-Dist: kdmt (>=1.0.68)
Requires-Dist: scikit-learn (==1.1.3)
Requires-Dist: py-dateinfer
Requires-Dist: overrides
Requires-Dist: Pyaml
Requires-Dist: joblib
Requires-Dist: tabulate
Requires-Dist: psutil
Requires-Dist: imblearn
Requires-Dist: seaborn
Requires-Dist: packaging
Requires-Dist: ipython
Requires-Dist: pypickle
Requires-Dist: python-louvain
Requires-Dist: category-encoders
Requires-Dist: networkx
Requires-Dist: dtreeviz
Requires-Dist: httpcore
Requires-Dist: httpx
Requires-Dist: httpx[http2]
Requires-Dist: xlsxwriter
Requires-Dist: synthcity
Requires-Dist: py-synthpop
Provides-Extra: all
Requires-Dist: eml-parser ; extra == 'all'
Requires-Dist: ipywidgets ; extra == 'all'
Requires-Dist: fasttext ; extra == 'all'
Requires-Dist: wordcloud ; extra == 'all'
Requires-Dist: sonopy ; extra == 'all'
Requires-Dist: dateparser ; extra == 'all'
Requires-Dist: gensim ; extra == 'all'
Requires-Dist: tensorflow (==2.8.0) ; extra == 'all'
Requires-Dist: pyLDAvis ; extra == 'all'
Provides-Extra: audio
Requires-Dist: sonopy ; extra == 'audio'
Provides-Extra: dnn
Requires-Dist: tensorflow (==2.8.0) ; extra == 'dnn'
Provides-Extra: nlp
Requires-Dist: gensim ; extra == 'nlp'
Requires-Dist: fasttext ; extra == 'nlp'
Requires-Dist: dateparser ; extra == 'nlp'
Requires-Dist: eml-parser ; extra == 'nlp'
Provides-Extra: notebook
Requires-Dist: ipywidgets ; extra == 'notebook'
Requires-Dist: pyLDAvis ; extra == 'notebook'
Requires-Dist: wordcloud ; extra == 'notebook'
